{
  "project_info": {
    "project_number": "184250757929",
    "firebase_url": "https://first-firebase-project-01.firebaseio.com",
    "project_id": "first-firebase-project-01",
    "storage_bucket": "first-firebase-project-01.appspot.com"
  },
  "client": [
    {
      "client_info": {
        "mobilesdk_app_id": "1:184250757929:android:3461c685eda94fb6ec3d38",
        "android_client_info": {
          "package_name": "com.example.pasc_event_project"
        }
      },
      "oauth_client": [
        {
          "client_id": "184250757929-ele3j4vqnjc95sk1t8p11451nsfiar13.apps.googleusercontent.com",
          "client_type": 3
        }
      ],
      "api_key": [
        {
          "current_key": "AIzaSyCQkGAKnJqRrMg_cua3_or2PUaY7NalfD4"
        }
      ],
      "services": {
        "appinvite_service": {
          "other_platform_oauth_client": [
            {
              "client_id": "184250757929-ele3j4vqnjc95sk1t8p11451nsfiar13.apps.googleusercontent.com",
              "client_type": 3
            }
          ]
        }
      }
    }
  ],
  "configuration_version": "1"
}